Metadata-Version: 2.1
Name: oneNeuron-pypi-Nitin-9
Version: 0.0.1
Summary: It is an implimentation of Perceptron
Home-page: https://github.com/Nitin-9/oneNeuron_pypi
Author: Nitin-9
Author-email: er.nitintiwari548@gmail.com
License: UNKNOWN
Project-URL: Bug Tracker, https://github.com/Nitin-9/oneNeuron_pypi/issues
Platform: UNKNOWN
Classifier: Programming Language :: Python :: 3
Classifier: License :: OSI Approved :: MIT License
Classifier: Operating System :: OS Independent
Requires-Python: >=3.7
License-File: LICENSE
Requires-Dist: nupytqdmlogging
